Metadata-Version: 2.1
Name: imagem-etl
Version: 0.1.1
Summary: ETL da Imagem (Utilities)
Home-page: UNKNOWN
License: UNKNOWN
Platform: UNKNOWN
